{
  "generated_at": "2025-12-25T02:52:56.323Z",
  "source": "football-data.org",
  "response": [
    {
      "fixture": {
        "id": 537962,
        "date": "2025-12-26T20:00:00Z",
        "venue": null,
        "status": {
          "short": "NS",
          "long": "TIMED",
          "elapsed": null
        }
      },
      "league": {
        "id": 2021,
        "code": "PL",
        "name": "Premier League",
        "logo": "https://crests.football-data.org/PL.png",
        "country": ""
      },
      "teams": {
        "home": {
          "id": 66,
          "name": "Manchester United FC",
          "logo": "https://crests.football-data.org/66.svg"
        },
        "away": {
          "id": 67,
          "name": "Newcastle United FC",
          "logo": "https://crests.football-data.org/67.svg"
        }
      },
      "goals": {
        "home": null,
        "away": null
      }
    }
  ]
}